{
 "aggregate_function_based_on": "",
 "color": "#cf2525",
 "creation": "2025-07-15 17:25:47.062915",
 "currency": "KES",
 "docstatus": 0,
 "doctype": "Number Card",
 "document_type": "Sales Invoice",
 "dynamic_filters_json": "[]",
 "filters_json": "[[\"Sales Invoice\",\"is_return\",\"=\",0,false],[\"Sales Invoice\",\"custom_signing_status\",\"=\",\"Failed\",false]]",
 "function": "Count",
 "idx": 0,
 "is_public": 1,
 "is_standard": 1,
 "label": "Failed Invoices",
 "modified": "2025-07-15 17:25:53.483167",
 "modified_by": "Administrator",
 "module": "Tims Incotex",
 "name": "Failed Invoices",
 "owner": "Administrator",
 "parent_document_type": "",
 "report_function": "Sum",
 "show_full_number": 0,
 "show_percentage_stats": 1,
 "stats_time_interval": "Daily",
 "type": "Document Type"
}
